{
  "scraped_at": "2026-07-05T19:16:35.556Z",
  "sources": [
    {
      "name": "ShichengBBS",
      "base_url": "https://www.shichengbbs.com"
    },
    {
      "name": "ShichengLuntan",
      "base_url": "https://www.shichengluntan.com"
    },
    {
      "name": "ShichengBao",
      "base_url": "https://www.shichengbao.com"
    }
  ],
  "total_count": 49,
  "listings": [
    {
      "id": "ShichengBao-4844",
      "title": "大型医疗器械公司操作员",
      "industry": "logistics",
      "tags": [],
      "contact": "",
      "contact_type": "phone",
      "source_url": "https://www.shichengbao.com/thread-4844-1-1.html",
      "source_platform": "ShichengBao",
      "posted_at": "2026-07-02T19:17:54.964Z",
      "scraped_at": "2026-07-05T19:16:35.556Z",
      "type": "employer",
      "company_name": "大型医疗器械公司",
      "job_title": "大型医疗器械公司操作员",
      "job_description": "大型医疗器械公司操作员",
      "required_skills": [],
      "location": "any",
      "budget_min": 0,
      "budget_max": 0,
      "urgency": "flexible"
    },
    {
      "id": "ShichengBao-4842",
      "title": "海鲜厨师2600包住",
      "industry": "other",
      "tags": [],
      "contact": "",
      "contact_type": "phone",
      "source_url": "https://www.shichengbao.com/thread-4842-1-1.html",
      "source_platform": "ShichengBao",
      "posted_at": "2026-07-02T19:17:54.965Z",
      "scraped_at": "2026-07-05T19:16:35.556Z",
      "type": "employer",
      "company_name": "",
      "job_title": "海鲜厨师2600包住",
      "job_description": "海鲜厨师2600包住",
      "required_skills": [],
      "location": "any",
      "budget_min": 0,
      "budget_max": 0,
      "urgency": "flexible"
    },
    {
      "id": "ShichengBao-4839",
      "title": "酒店保洁员2300包吃住",
      "industry": "other",
      "tags": [],
      "contact": "",
      "contact_type": "phone",
      "source_url": "https://www.shichengbao.com/thread-4839-1-1.html",
      "source_platform": "ShichengBao",
      "posted_at": "2026-07-02T19:17:54.965Z",
      "scraped_at": "2026-07-05T19:16:35.556Z",
      "type": "employer",
      "company_name": "",
      "job_title": "酒店保洁员2300包吃住",
      "job_description": "酒店保洁员2300包吃住",
      "required_skills": [],
      "location": "any",
      "budget_min": 0,
      "budget_max": 0,
      "urgency": "flexible"
    },
    {
      "id": "ShichengBao-4838",
      "title": "餐馆厨师",
      "industry": "other",
      "tags": [],
      "contact": "",
      "contact_type": "phone",
      "source_url": "https://www.shichengbao.com/thread-4838-1-1.html",
      "source_platform": "ShichengBao",
      "posted_at": "2026-07-02T19:17:54.965Z",
      "scraped_at": "2026-07-05T19:16:35.556Z",
      "type": "employer",
      "company_name": "",
      "job_title": "餐馆厨师",
      "job_description": "餐馆厨师",
      "required_skills": [],
      "location": "any",
      "budget_min": 0,
      "budget_max": 0,
      "urgency": "flexible"
    },
    {
      "id": "ShichengBao-4836",
      "title": "叉车兼普工",
      "industry": "logistics",
      "tags": [],
      "contact": "",
      "contact_type": "phone",
      "source_url": "https://www.shichengbao.com/thread-4836-1-1.html",
      "source_platform": "ShichengBao",
      "posted_at": "2026-07-02T19:17:54.965Z",
      "scraped_at": "2026-07-05T19:16:35.556Z",
      "type": "employer",
      "company_name": "",
      "job_title": "叉车兼普工",
      "job_description": "叉车兼普工",
      "required_skills": [],
      "location": "any",
      "budget_min": 0,
      "budget_max": 0,
      "urgency": "flexible"
    },
    {
      "id": "ShichengBao-4835",
      "title": "圣淘沙高薪岗位",
      "industry": "other",
      "tags": [],
      "contact": "",
      "contact_type": "phone",
      "source_url": "https://www.shichengbao.com/thread-4835-1-1.html",
      "source_platform": "ShichengBao",
      "posted_at": "2026-07-02T19:17:54.965Z",
      "scraped_at": "2026-07-05T19:16:35.556Z",
      "type": "employer",
      "company_name": "",
      "job_title": "圣淘沙高薪岗位",
      "job_description": "圣淘沙高薪岗位",
      "required_skills": [],
      "location": "any",
      "budget_min": 0,
      "budget_max": 0,
      "urgency": "flexible"
    },
    {
      "id": "ShichengBao-4833",
      "title": "闲暇时间赚零花钱，跨境电商客服兼职等你来",
      "industry": "retail",
      "tags": [],
      "contact": "",
      "contact_type": "phone",
      "source_url": "https://www.shichengbao.com/thread-4833-1-1.html",
      "source_platform": "ShichengBao",
      "posted_at": "2026-07-02T19:17:54.965Z",
      "scraped_at": "2026-07-05T19:16:35.556Z",
      "type": "employer",
      "company_name": "",
      "job_title": "闲暇时间赚零花钱，跨境电商客服兼职等你来",
      "job_description": "闲暇时间赚零花钱，跨境电商客服兼职等你来",
      "required_skills": [],
      "location": "any",
      "budget_min": 0,
      "budget_max": 0,
      "urgency": "flexible"
    },
    {
      "id": "ShichengBao-4832",
      "title": "51岁以下生产操作工",
      "industry": "other",
      "tags": [],
      "contact": "",
      "contact_type": "phone",
      "source_url": "https://www.shichengbao.com/thread-4832-1-1.html",
      "source_platform": "ShichengBao",
      "posted_at": "2026-07-02T19:17:54.965Z",
      "scraped_at": "2026-07-05T19:16:35.556Z",
      "type": "employer",
      "company_name": "",
      "job_title": "51岁以下生产操作工",
      "job_description": "51岁以下生产操作工",
      "required_skills": [],
      "location": "any",
      "budget_min": 0,
      "budget_max": 0,
      "urgency": "flexible"
    },
    {
      "id": "ShichengBao-4829",
      "title": "机场服务员工",
      "industry": "fnb",
      "tags": [],
      "contact": "",
      "contact_type": "phone",
      "source_url": "https://www.shichengbao.com/thread-4829-1-1.html",
      "source_platform": "ShichengBao",
      "posted_at": "2026-07-01T19:17:54.965Z",
      "scraped_at": "2026-07-05T19:16:35.556Z",
      "type": "employer",
      "company_name": "",
      "job_title": "机场服务员工",
      "job_description": "机场服务员工",
      "required_skills": [],
      "location": "any",
      "budget_min": 0,
      "budget_max": 0,
      "urgency": "flexible"
    },
    {
      "id": "ShichengBao-4828",
      "title": "中餐厅主管",
      "industry": "other",
      "tags": [],
      "contact": "",
      "contact_type": "phone",
      "source_url": "https://www.shichengbao.com/thread-4828-1-1.html",
      "source_platform": "ShichengBao",
      "posted_at": "2026-07-01T19:17:54.965Z",
      "scraped_at": "2026-07-05T19:16:35.556Z",
      "type": "employer",
      "company_name": "",
      "job_title": "中餐厅主管",
      "job_description": "中餐厅主管",
      "required_skills": [],
      "location": "any",
      "budget_min": 0,
      "budget_max": 0,
      "urgency": "flexible"
    },
    {
      "id": "ShichengBao-4827",
      "title": "酒店客房清理服务员",
      "industry": "fnb",
      "tags": [],
      "contact": "",
      "contact_type": "phone",
      "source_url": "https://www.shichengbao.com/thread-4827-1-1.html",
      "source_platform": "ShichengBao",
      "posted_at": "2026-07-01T19:17:54.965Z",
      "scraped_at": "2026-07-05T19:16:35.556Z",
      "type": "employer",
      "company_name": "",
      "job_title": "酒店客房清理服务员",
      "job_description": "酒店客房清理服务员",
      "required_skills": [],
      "location": "any",
      "budget_min": 0,
      "budget_max": 0,
      "urgency": "flexible"
    },
    {
      "id": "ShichengBao-4826",
      "title": "美容美体师",
      "industry": "beauty",
      "tags": [],
      "contact": "",
      "contact_type": "phone",
      "source_url": "https://www.shichengbao.com/thread-4826-1-1.html",
      "source_platform": "ShichengBao",
      "posted_at": "2026-07-01T19:17:54.965Z",
      "scraped_at": "2026-07-05T19:16:35.556Z",
      "type": "employer",
      "company_name": "",
      "job_title": "美容美体师",
      "job_description": "美容美体师",
      "required_skills": [],
      "location": "any",
      "budget_min": 0,
      "budget_max": 0,
      "urgency": "flexible"
    },
    {
      "id": "ShichengBao-4825",
      "title": "蛋糕 糕点学徒工",
      "industry": "other",
      "tags": [],
      "contact": "",
      "contact_type": "phone",
      "source_url": "https://www.shichengbao.com/thread-4825-1-1.html",
      "source_platform": "ShichengBao",
      "posted_at": "2026-07-01T19:17:54.965Z",
      "scraped_at": "2026-07-05T19:16:35.556Z",
      "type": "employer",
      "company_name": "",
      "job_title": "蛋糕 糕点学徒工",
      "job_description": "蛋糕 糕点学徒工",
      "required_skills": [],
      "location": "any",
      "budget_min": 0,
      "budget_max": 0,
      "urgency": "flexible"
    },
    {
      "id": "ShichengBao-4824",
      "title": "4号集装箱学徒",
      "industry": "other",
      "tags": [],
      "contact": "",
      "contact_type": "phone",
      "source_url": "https://www.shichengbao.com/thread-4824-1-1.html",
      "source_platform": "ShichengBao",
      "posted_at": "2026-07-01T19:17:54.965Z",
      "scraped_at": "2026-07-05T19:16:35.556Z",
      "type": "employer",
      "company_name": "",
      "job_title": "4号集装箱学徒",
      "job_description": "4号集装箱学徒",
      "required_skills": [],
      "location": "any",
      "budget_min": 0,
      "budget_max": 0,
      "urgency": "flexible"
    },
    {
      "id": "ShichengBao-4823",
      "title": "物流公司4号司机",
      "industry": "driver",
      "tags": [],
      "contact": "",
      "contact_type": "phone",
      "source_url": "https://www.shichengbao.com/thread-4823-1-1.html",
      "source_platform": "ShichengBao",
      "posted_at": "2026-07-01T19:17:54.965Z",
      "scraped_at": "2026-07-05T19:16:35.556Z",
      "type": "employer",
      "company_name": "物流公司",
      "job_title": "物流公司4号司机",
      "job_description": "物流公司4号司机",
      "required_skills": [],
      "location": "any",
      "budget_min": 0,
      "budget_max": 0,
      "urgency": "flexible"
    },
    {
      "id": "ShichengBao-4820",
      "title": "室内装修工  木工优先",
      "industry": "construction",
      "tags": [],
      "contact": "",
      "contact_type": "phone",
      "source_url": "https://www.shichengbao.com/thread-4820-1-1.html",
      "source_platform": "ShichengBao",
      "posted_at": "2026-07-01T19:17:54.965Z",
      "scraped_at": "2026-07-05T19:16:35.556Z",
      "type": "employer",
      "company_name": "",
      "job_title": "室内装修工  木工优先",
      "job_description": "室内装修工  木工优先",
      "required_skills": [],
      "location": "any",
      "budget_min": 0,
      "budget_max": 0,
      "urgency": "flexible"
    },
    {
      "id": "ShichengBao-4818",
      "title": "档口收银",
      "industry": "other",
      "tags": [],
      "contact": "",
      "contact_type": "phone",
      "source_url": "https://www.shichengbao.com/thread-4818-1-1.html",
      "source_platform": "ShichengBao",
      "posted_at": "2026-07-01T19:17:54.965Z",
      "scraped_at": "2026-07-05T19:16:35.556Z",
      "type": "employer",
      "company_name": "",
      "job_title": "档口收银",
      "job_description": "档口收银",
      "required_skills": [],
      "location": "any",
      "budget_min": 0,
      "budget_max": 0,
      "urgency": "flexible"
    },
    {
      "id": "ShichengBao-4817",
      "title": "海外华人专属|居家线上兼职，灵活办公增收",
      "industry": "other",
      "tags": [],
      "contact": "",
      "contact_type": "phone",
      "source_url": "https://www.shichengbao.com/thread-4817-1-1.html",
      "source_platform": "ShichengBao",
      "posted_at": "2026-07-01T19:17:54.965Z",
      "scraped_at": "2026-07-05T19:16:35.556Z",
      "type": "employer",
      "company_name": "",
      "job_title": "海外华人专属|居家线上兼职，灵活办公增收",
      "job_description": "海外华人专属|居家线上兼职，灵活办公增收",
      "required_skills": [],
      "location": "any",
      "budget_min": 0,
      "budget_max": 0,
      "urgency": "flexible"
    },
    {
      "id": "ShichengBao-4816",
      "title": "无需外出坐班办公，跨境运营岗位热招",
      "industry": "other",
      "tags": [],
      "contact": "",
      "contact_type": "phone",
      "source_url": "https://www.shichengbao.com/thread-4816-1-1.html",
      "source_platform": "ShichengBao",
      "posted_at": "2026-07-01T19:17:54.965Z",
      "scraped_at": "2026-07-05T19:16:35.556Z",
      "type": "employer",
      "company_name": "",
      "job_title": "无需外出坐班办公，跨境运营岗位热招",
      "job_description": "无需外出坐班办公，跨境运营岗位热招",
      "required_skills": [],
      "location": "any",
      "budget_min": 0,
      "budget_max": 0,
      "urgency": "flexible"
    },
    {
      "id": "ShichengBao-4811",
      "title": "餐厅服务员",
      "industry": "fnb",
      "tags": [],
      "contact": "",
      "contact_type": "phone",
      "source_url": "https://www.shichengbao.com/thread-4811-1-1.html",
      "source_platform": "ShichengBao",
      "posted_at": "2026-06-30T19:17:54.965Z",
      "scraped_at": "2026-07-05T19:16:35.556Z",
      "type": "employer",
      "company_name": "",
      "job_title": "餐厅服务员",
      "job_description": "餐厅服务员",
      "required_skills": [],
      "location": "any",
      "budget_min": 0,
      "budget_max": 0,
      "urgency": "flexible"
    },
    {
      "id": "ShichengBao-4810",
      "title": "食品厂文员",
      "industry": "other",
      "tags": [],
      "contact": "",
      "contact_type": "phone",
      "source_url": "https://www.shichengbao.com/thread-4810-1-1.html",
      "source_platform": "ShichengBao",
      "posted_at": "2026-06-30T19:17:54.965Z",
      "scraped_at": "2026-07-05T19:16:35.556Z",
      "type": "employer",
      "company_name": "",
      "job_title": "食品厂文员",
      "job_description": "食品厂文员",
      "required_skills": [],
      "location": "any",
      "budget_min": 0,
      "budget_max": 0,
      "urgency": "flexible"
    },
    {
      "id": "ShichengBao-4808",
      "title": "国内司机",
      "industry": "driver",
      "tags": [],
      "contact": "",
      "contact_type": "phone",
      "source_url": "https://www.shichengbao.com/thread-4808-1-1.html",
      "source_platform": "ShichengBao",
      "posted_at": "2026-06-30T19:17:54.966Z",
      "scraped_at": "2026-07-05T19:16:35.556Z",
      "type": "employer",
      "company_name": "",
      "job_title": "国内司机",
      "job_description": "国内司机",
      "required_skills": [],
      "location": "any",
      "budget_min": 0,
      "budget_max": 0,
      "urgency": "flexible"
    },
    {
      "id": "ShichengBao-4806",
      "title": "WP 服务员",
      "industry": "fnb",
      "tags": [],
      "contact": "",
      "contact_type": "phone",
      "source_url": "https://www.shichengbao.com/thread-4806-1-1.html",
      "source_platform": "ShichengBao",
      "posted_at": "2026-06-30T19:17:54.966Z",
      "scraped_at": "2026-07-05T19:16:35.556Z",
      "type": "employer",
      "company_name": "",
      "job_title": "WP 服务员",
      "job_description": "WP 服务员",
      "required_skills": [],
      "location": "any",
      "budget_min": 0,
      "budget_max": 0,
      "urgency": "flexible"
    },
    {
      "id": "ShichengBao-4805",
      "title": "包装服务商普工学徒",
      "industry": "logistics",
      "tags": [],
      "contact": "",
      "contact_type": "phone",
      "source_url": "https://www.shichengbao.com/thread-4805-1-1.html",
      "source_platform": "ShichengBao",
      "posted_at": "2026-06-30T19:17:54.966Z",
      "scraped_at": "2026-07-05T19:16:35.556Z",
      "type": "employer",
      "company_name": "",
      "job_title": "包装服务商普工学徒",
      "job_description": "包装服务商普工学徒",
      "required_skills": [],
      "location": "any",
      "budget_min": 0,
      "budget_max": 0,
      "urgency": "flexible"
    },
    {
      "id": "ShichengBao-4804",
      "title": "包吃包住食品厂女杂工",
      "industry": "other",
      "tags": [],
      "contact": "",
      "contact_type": "phone",
      "source_url": "https://www.shichengbao.com/thread-4804-1-1.html",
      "source_platform": "ShichengBao",
      "posted_at": "2026-06-30T19:17:54.966Z",
      "scraped_at": "2026-07-05T19:16:35.556Z",
      "type": "employer",
      "company_name": "",
      "job_title": "包吃包住食品厂女杂工",
      "job_description": "包吃包住食品厂女杂工",
      "required_skills": [],
      "location": "any",
      "budget_min": 0,
      "budget_max": 0,
      "urgency": "flexible"
    },
    {
      "id": "ShichengBao-4802",
      "title": "WP蛋糕助手兼普工",
      "industry": "logistics",
      "tags": [],
      "contact": "",
      "contact_type": "phone",
      "source_url": "https://www.shichengbao.com/thread-4802-1-1.html",
      "source_platform": "ShichengBao",
      "posted_at": "2026-06-30T19:17:54.966Z",
      "scraped_at": "2026-07-05T19:16:35.556Z",
      "type": "employer",
      "company_name": "",
      "job_title": "WP蛋糕助手兼普工",
      "job_description": "WP蛋糕助手兼普工",
      "required_skills": [],
      "location": "any",
      "budget_min": 0,
      "budget_max": 0,
      "urgency": "flexible"
    },
    {
      "id": "ShichengBao-4801",
      "title": "工厂普工",
      "industry": "logistics",
      "tags": [],
      "contact": "",
      "contact_type": "phone",
      "source_url": "https://www.shichengbao.com/thread-4801-1-1.html",
      "source_platform": "ShichengBao",
      "posted_at": "2026-06-30T19:17:54.966Z",
      "scraped_at": "2026-07-05T19:16:35.556Z",
      "type": "employer",
      "company_name": "",
      "job_title": "工厂普工",
      "job_description": "工厂普工",
      "required_skills": [],
      "location": "any",
      "budget_min": 0,
      "budget_max": 0,
      "urgency": "flexible"
    },
    {
      "id": "ShichengBao-4799",
      "title": "麻辣香锅女收银员",
      "industry": "other",
      "tags": [],
      "contact": "",
      "contact_type": "phone",
      "source_url": "https://www.shichengbao.com/thread-4799-1-1.html",
      "source_platform": "ShichengBao",
      "posted_at": "2026-06-30T19:17:54.966Z",
      "scraped_at": "2026-07-05T19:16:35.556Z",
      "type": "employer",
      "company_name": "",
      "job_title": "麻辣香锅女收银员",
      "job_description": "麻辣香锅女收银员",
      "required_skills": [],
      "location": "any",
      "budget_min": 0,
      "budget_max": 0,
      "urgency": "flexible"
    },
    {
      "id": "ShichengBao-4796",
      "title": "三号按摩店",
      "industry": "beauty",
      "tags": [],
      "contact": "",
      "contact_type": "phone",
      "source_url": "https://www.shichengbao.com/thread-4796-1-1.html",
      "source_platform": "ShichengBao",
      "posted_at": "2026-06-30T19:17:54.966Z",
      "scraped_at": "2026-07-05T19:16:35.556Z",
      "type": "employer",
      "company_name": "三号按摩店",
      "job_title": "三号按摩店",
      "job_description": "三号按摩店",
      "required_skills": [],
      "location": "any",
      "budget_min": 0,
      "budget_max": 0,
      "urgency": "flexible"
    },
    {
      "id": "ShichengBao-4795",
      "title": "四号司机",
      "industry": "driver",
      "tags": [],
      "contact": "",
      "contact_type": "phone",
      "source_url": "https://www.shichengbao.com/thread-4795-1-1.html",
      "source_platform": "ShichengBao",
      "posted_at": "2026-06-30T19:17:54.966Z",
      "scraped_at": "2026-07-05T19:16:35.556Z",
      "type": "employer",
      "company_name": "",
      "job_title": "四号司机",
      "job_description": "四号司机",
      "required_skills": [],
      "location": "any",
      "budget_min": 0,
      "budget_max": 0,
      "urgency": "flexible"
    },
    {
      "id": "ShichengBao-4789",
      "title": "酒店保洁员",
      "industry": "other",
      "tags": [],
      "contact": "",
      "contact_type": "phone",
      "source_url": "https://www.shichengbao.com/thread-4789-1-1.html",
      "source_platform": "ShichengBao",
      "posted_at": "2026-06-29T19:17:54.966Z",
      "scraped_at": "2026-07-05T19:16:35.556Z",
      "type": "employer",
      "company_name": "",
      "job_title": "酒店保洁员",
      "job_description": "酒店保洁员",
      "required_skills": [],
      "location": "any",
      "budget_min": 0,
      "budget_max": 0,
      "urgency": "flexible"
    },
    {
      "id": "ShichengBao-4788",
      "title": "餐厅/食堂助理",
      "industry": "other",
      "tags": [],
      "contact": "",
      "contact_type": "phone",
      "source_url": "https://www.shichengbao.com/thread-4788-1-1.html",
      "source_platform": "ShichengBao",
      "posted_at": "2026-06-29T19:17:54.966Z",
      "scraped_at": "2026-07-05T19:16:35.556Z",
      "type": "employer",
      "company_name": "",
      "job_title": "餐厅/食堂助理",
      "job_description": "餐厅/食堂助理",
      "required_skills": [],
      "location": "any",
      "budget_min": 0,
      "budget_max": 0,
      "urgency": "flexible"
    },
    {
      "id": "ShichengBao-4542",
      "title": "按摩学徒",
      "industry": "beauty",
      "tags": [],
      "contact": "",
      "contact_type": "phone",
      "source_url": "https://www.shichengbao.com/thread-4542-1-1.html",
      "source_platform": "ShichengBao",
      "posted_at": "2026-06-09T00:00:00.000Z",
      "scraped_at": "2026-07-05T19:16:35.556Z",
      "type": "employer",
      "company_name": "",
      "job_title": "按摩学徒",
      "job_description": "按摩学徒",
      "required_skills": [],
      "location": "any",
      "budget_min": 0,
      "budget_max": 0,
      "urgency": "flexible"
    },
    {
      "id": "ShichengBao-4787",
      "title": "汽车维修",
      "industry": "other",
      "tags": [],
      "contact": "",
      "contact_type": "phone",
      "source_url": "https://www.shichengbao.com/thread-4787-1-1.html",
      "source_platform": "ShichengBao",
      "posted_at": "2026-06-29T19:17:54.966Z",
      "scraped_at": "2026-07-05T19:16:35.556Z",
      "type": "employer",
      "company_name": "",
      "job_title": "汽车维修",
      "job_description": "汽车维修",
      "required_skills": [],
      "location": "any",
      "budget_min": 0,
      "budget_max": 0,
      "urgency": "flexible"
    },
    {
      "id": "ShichengBao-4784",
      "title": "在家就能做!简单上传商品+回复消息，时间自由",
      "industry": "other",
      "tags": [],
      "contact": "",
      "contact_type": "phone",
      "source_url": "https://www.shichengbao.com/thread-4784-1-1.html",
      "source_platform": "ShichengBao",
      "posted_at": "2026-06-29T19:17:54.966Z",
      "scraped_at": "2026-07-05T19:16:35.556Z",
      "type": "employer",
      "company_name": "",
      "job_title": "在家就能做!简单上传商品+回复消息，时间自由",
      "job_description": "在家就能做!简单上传商品+回复消息，时间自由",
      "required_skills": [],
      "location": "any",
      "budget_min": 0,
      "budget_max": 0,
      "urgency": "flexible"
    },
    {
      "id": "ShichengBao-4781",
      "title": "串串烧烤师傅",
      "industry": "other",
      "tags": [],
      "contact": "",
      "contact_type": "phone",
      "source_url": "https://www.shichengbao.com/thread-4781-1-1.html",
      "source_platform": "ShichengBao",
      "posted_at": "2026-06-28T19:17:54.966Z",
      "scraped_at": "2026-07-05T19:16:35.556Z",
      "type": "employer",
      "company_name": "",
      "job_title": "串串烧烤师傅",
      "job_description": "串串烧烤师傅",
      "required_skills": [],
      "location": "any",
      "budget_min": 0,
      "budget_max": 0,
      "urgency": "flexible"
    },
    {
      "id": "ShichengBao-4778",
      "title": "摊位普工",
      "industry": "logistics",
      "tags": [],
      "contact": "",
      "contact_type": "phone",
      "source_url": "https://www.shichengbao.com/thread-4778-1-1.html",
      "source_platform": "ShichengBao",
      "posted_at": "2026-06-28T19:17:54.966Z",
      "scraped_at": "2026-07-05T19:16:35.556Z",
      "type": "employer",
      "company_name": "",
      "job_title": "摊位普工",
      "job_description": "摊位普工",
      "required_skills": [],
      "location": "any",
      "budget_min": 0,
      "budget_max": 0,
      "urgency": "flexible"
    },
    {
      "id": "ShichengBao-4776",
      "title": "男餐厅帮厨",
      "industry": "other",
      "tags": [],
      "contact": "",
      "contact_type": "phone",
      "source_url": "https://www.shichengbao.com/thread-4776-1-1.html",
      "source_platform": "ShichengBao",
      "posted_at": "2026-06-28T19:17:54.966Z",
      "scraped_at": "2026-07-05T19:16:35.556Z",
      "type": "employer",
      "company_name": "",
      "job_title": "男餐厅帮厨",
      "job_description": "男餐厅帮厨",
      "required_skills": [],
      "location": "any",
      "budget_min": 0,
      "budget_max": 0,
      "urgency": "flexible"
    },
    {
      "id": "ShichengBao-4775",
      "title": "电焊工兼普工",
      "industry": "logistics",
      "tags": [],
      "contact": "",
      "contact_type": "phone",
      "source_url": "https://www.shichengbao.com/thread-4775-1-1.html",
      "source_platform": "ShichengBao",
      "posted_at": "2026-06-28T19:17:54.966Z",
      "scraped_at": "2026-07-05T19:16:35.556Z",
      "type": "employer",
      "company_name": "",
      "job_title": "电焊工兼普工",
      "job_description": "电焊工兼普工",
      "required_skills": [],
      "location": "any",
      "budget_min": 0,
      "budget_max": 0,
      "urgency": "flexible"
    },
    {
      "id": "ShichengBao-4772",
      "title": "跨境电商代理，合作共赢",
      "industry": "other",
      "tags": [],
      "contact": "",
      "contact_type": "phone",
      "source_url": "https://www.shichengbao.com/thread-4772-1-1.html",
      "source_platform": "ShichengBao",
      "posted_at": "2026-06-28T19:17:54.966Z",
      "scraped_at": "2026-07-05T19:16:35.556Z",
      "type": "employer",
      "company_name": "",
      "job_title": "跨境电商代理，合作共赢",
      "job_description": "跨境电商代理，合作共赢",
      "required_skills": [],
      "location": "any",
      "budget_min": 0,
      "budget_max": 0,
      "urgency": "flexible"
    },
    {
      "id": "ShichengBao-4771",
      "title": "日韩餐档口帮厨",
      "industry": "other",
      "tags": [],
      "contact": "",
      "contact_type": "phone",
      "source_url": "https://www.shichengbao.com/thread-4771-1-1.html",
      "source_platform": "ShichengBao",
      "posted_at": "2026-06-28T19:17:54.966Z",
      "scraped_at": "2026-07-05T19:16:35.556Z",
      "type": "employer",
      "company_name": "",
      "job_title": "日韩餐档口帮厨",
      "job_description": "日韩餐档口帮厨",
      "required_skills": [],
      "location": "any",
      "budget_min": 0,
      "budget_max": 0,
      "urgency": "flexible"
    },
    {
      "id": "ShichengBao-4770",
      "title": "电商客服・适合留学生 / 宝妈 / 上班族",
      "industry": "retail",
      "tags": [],
      "contact": "",
      "contact_type": "phone",
      "source_url": "https://www.shichengbao.com/thread-4770-1-1.html",
      "source_platform": "ShichengBao",
      "posted_at": "2026-06-28T19:17:54.966Z",
      "scraped_at": "2026-07-05T19:16:35.556Z",
      "type": "employer",
      "company_name": "",
      "job_title": "电商客服・适合留学生 / 宝妈 / 上班族",
      "job_description": "电商客服・适合留学生 / 宝妈 / 上班族",
      "required_skills": [],
      "location": "any",
      "budget_min": 0,
      "budget_max": 0,
      "urgency": "flexible"
    },
    {
      "id": "ShichengBao-4765",
      "title": "英文要求不高的销售",
      "industry": "retail",
      "tags": [],
      "contact": "",
      "contact_type": "phone",
      "source_url": "https://www.shichengbao.com/thread-4765-1-1.html",
      "source_platform": "ShichengBao",
      "posted_at": "2026-06-27T00:00:00.000Z",
      "scraped_at": "2026-07-05T19:16:35.556Z",
      "type": "employer",
      "company_name": "",
      "job_title": "英文要求不高的销售",
      "job_description": "英文要求不高的销售",
      "required_skills": [],
      "location": "any",
      "budget_min": 0,
      "budget_max": 0,
      "urgency": "flexible"
    },
    {
      "id": "ShichengBao-4764",
      "title": "不影响主业的副业，轻松增加收入",
      "industry": "other",
      "tags": [],
      "contact": "",
      "contact_type": "phone",
      "source_url": "https://www.shichengbao.com/thread-4764-1-1.html",
      "source_platform": "ShichengBao",
      "posted_at": "2026-06-27T00:00:00.000Z",
      "scraped_at": "2026-07-05T19:16:35.556Z",
      "type": "employer",
      "company_name": "",
      "job_title": "不影响主业的副业，轻松增加收入",
      "job_description": "不影响主业的副业，轻松增加收入",
      "required_skills": [],
      "location": "any",
      "budget_min": 0,
      "budget_max": 0,
      "urgency": "flexible"
    },
    {
      "id": "ShichengBao-4763",
      "title": "夜班麻辣烫二厨",
      "industry": "other",
      "tags": [],
      "contact": "",
      "contact_type": "phone",
      "source_url": "https://www.shichengbao.com/thread-4763-1-1.html",
      "source_platform": "ShichengBao",
      "posted_at": "2026-06-27T00:00:00.000Z",
      "scraped_at": "2026-07-05T19:16:35.556Z",
      "type": "employer",
      "company_name": "",
      "job_title": "夜班麻辣烫二厨",
      "job_description": "夜班麻辣烫二厨",
      "required_skills": [],
      "location": "any",
      "budget_min": 0,
      "budget_max": 0,
      "urgency": "flexible"
    },
    {
      "id": "ShichengBao-4761",
      "title": "诚聘订单处理员",
      "industry": "other",
      "tags": [],
      "contact": "",
      "contact_type": "phone",
      "source_url": "https://www.shichengbao.com/thread-4761-1-1.html",
      "source_platform": "ShichengBao",
      "posted_at": "2026-06-27T00:00:00.000Z",
      "scraped_at": "2026-07-05T19:16:35.556Z",
      "type": "employer",
      "company_name": "",
      "job_title": "诚聘订单处理员",
      "job_description": "诚聘订单处理员",
      "required_skills": [],
      "location": "any",
      "budget_min": 0,
      "budget_max": 0,
      "urgency": "flexible"
    },
    {
      "id": "ShichengBao-4757",
      "title": "不影响您正常的工作和生活，利用闲暇的时 间在家兼职",
      "industry": "other",
      "tags": [],
      "contact": "",
      "contact_type": "phone",
      "source_url": "https://www.shichengbao.com/thread-4757-1-1.html",
      "source_platform": "ShichengBao",
      "posted_at": "2026-06-26T00:00:00.000Z",
      "scraped_at": "2026-07-05T19:16:35.556Z",
      "type": "employer",
      "company_name": "",
      "job_title": "不影响您正常的工作和生活，利用闲暇的时 间在家兼职",
      "job_description": "不影响您正常的工作和生活，利用闲暇的时 间在家兼职",
      "required_skills": [],
      "location": "any",
      "budget_min": 0,
      "budget_max": 0,
      "urgency": "flexible"
    },
    {
      "id": "ShichengBao-4756",
      "title": "男女摊位助手",
      "industry": "other",
      "tags": [],
      "contact": "",
      "contact_type": "phone",
      "source_url": "https://www.shichengbao.com/thread-4756-1-1.html",
      "source_platform": "ShichengBao",
      "posted_at": "2026-06-26T00:00:00.000Z",
      "scraped_at": "2026-07-05T19:16:35.556Z",
      "type": "employer",
      "company_name": "男女摊位",
      "job_title": "男女摊位助手",
      "job_description": "男女摊位助手",
      "required_skills": [],
      "location": "any",
      "budget_min": 0,
      "budget_max": 0,
      "urgency": "flexible"
    },
    {
      "id": "ShichengBao-4754",
      "title": "食品厂普工",
      "industry": "logistics",
      "tags": [],
      "contact": "",
      "contact_type": "phone",
      "source_url": "https://www.shichengbao.com/thread-4754-1-1.html",
      "source_platform": "ShichengBao",
      "posted_at": "2026-06-26T00:00:00.000Z",
      "scraped_at": "2026-07-05T19:16:35.556Z",
      "type": "employer",
      "company_name": "",
      "job_title": "食品厂普工",
      "job_description": "食品厂普工",
      "required_skills": [],
      "location": "any",
      "budget_min": 0,
      "budget_max": 0,
      "urgency": "flexible"
    }
  ]
}
